LICENSE.txt
MANIFEST.in
README.md
setup.py
Joseph_Automation.egg-info/PKG-INFO
Joseph_Automation.egg-info/SOURCES.txt
Joseph_Automation.egg-info/dependency_links.txt
Joseph_Automation.egg-info/requires.txt
Joseph_Automation.egg-info/top_level.txt
joseph/__init__.py
joseph/__main__.py
joseph/config.py
joseph/constants.py
joseph/core.py
joseph/exceptions.py