Metadata-Version: 1.0
Name: Joseph-Automation
Version: 0.0.1
Summary: A home automation platform with framework aspirations
Home-page: https://github.com/NiekKeijzer/joseph
Author: Niek Keijzer
Author-email: info@niekkeijzer.com
License: MIT
Platform: UNKNOWN
